[
 {
  "qlearing": {
   "path": [
    2,
    4
   ],
   "distance": 4193.122452021084,
   "num_satellites": 2,
   "true_distance": 4193.122452021084,
   "number_of_congested_satellites": {
    "low": 2,
    "medium": 0,
    "high": 0
   },
   "number_of_delayed_satellites": {
    "low": 0,
    "medium": 2,
    "high": 0
   }
  },
  "flood": {
   "path": [
    [
     2,
     3
    ],
    [
     2,
     4
    ]
   ],
   "distance": 2983.910600656734,
   "num_satellites": 2,
   "true_distance": 4193.122452021084,
   "number_of_congested_satellites": {
    "low": 4,
    "medium": 0,
    "high": 0
   },
   "number_of_delayed_satellites": {
    "low": 0,
    "medium": 4,
    "high": 0
   }
  },
  "dqn": {
   "path": [
    2,
    4
   ],
   "distance": 4193.122452021084,
   "num_satellites": 2,
   "true_distance": 4193.122452021084,
   "number_of_congested_satellites": {
    "low": 2,
    "medium": 0,
    "high": 0
   },
   "number_of_delayed_satellites": {
    "low": 0,
    "medium": 2,
    "high": 0
   }
  }
 },
 {
  "qlearing": {
   "path": [
    1,
    16,
    5,
    9
   ],
   "distance": 14955.536112245925,
   "num_satellites": 4,
   "true_distance": 13230.10763119681,
   "number_of_congested_satellites": {
    "low": 6,
    "medium": 0,
    "high": 0
   },
   "number_of_delayed_satellites": {
    "low": 0,
    "medium": 4,
    "high": 2
   }
  },
  "flood": {
   "path": [
    [
     1,
     0
    ],
    [
     1,
     6
    ],
    [
     1,
     7
    ],
    [
     1,
     10
    ],
    [
     1,
     11
    ],
    [
     1,
     12
    ],
    [
     1,
     15
    ],
    [
     1,
     16
    ],
    [
     1,
     19
    ],
    [
     1,
     21
    ],
    [
     1,
     28
    ],
    [
     1,
     29
    ],
    [
     1,
     30
    ],
    [
     1,
     35
    ],
    [
     1,
     36
    ],
    [
     1,
     37
    ],
    [
     1,
     39
    ],
    [
     1,
     43
    ],
    [
     1,
     49
    ],
    [
     0,
     4
    ],
    [
     0,
     8
    ],
    [
     0,
     13
    ],
    [
     0,
     17
    ],
    [
     0,
     22
    ],
    [
     0,
     24
    ],
    [
     0,
     32
    ],
    [
     0,
     34
    ],
    [
     0,
     40
    ],
    [
     0,
     41
    ],
    [
     0,
     42
    ],
    [
     0,
     44
    ],
    [
     0,
     48
    ],
    [
     11,
     18
    ],
    [
     11,
     20
    ],
    [
     11,
     47
    ],
    [
     12,
     14
    ],
    [
     12,
     25
    ],
    [
     12,
     26
    ],
    [
     12,
     33
    ],
    [
     16,
     5
    ],
    [
     4,
     2
    ],
    [
     4,
     3
    ],
    [
     4,
     23
    ],
    [
     4,
     27
    ],
    [
     4,
     31
    ],
    [
     4,
     45
    ],
    [
     4,
     46
    ],
    [
     17,
     9
    ]
   ],
   "distance": 256481.33167696066,
   "num_satellites": 48,
   "true_distance": 13230.10763119681,
   "number_of_congested_satellites": {
    "low": 96,
    "medium": 0,
    "high": 0
   },
   "number_of_delayed_satellites": {
    "low": 0,
    "medium": 40,
    "high": 56
   }
  },
  "dqn": {
   "path": [
    1,
    0,
    44,
    27,
    44,
    27,
    44,
    27,
    49,
    1,
    26,
    27,
    44,
    27,
    44,
    9
   ],
   "distance": 122664.98941527308,
   "num_satellites": 16,
   "true_distance": 13230.10763119681,
   "number_of_congested_satellites": {
    "low": 30,
    "medium": 0,
    "high": 0
   },
   "number_of_delayed_satellites": {
    "low": 0,
    "medium": 4,
    "high": 26
   }
  }
 },
 {
  "qlearing": {
   "path": [
    7,
    0,
    22,
    0,
    10,
    24,
    42,
    0,
    10,
    29,
    16,
    43,
    16,
    19,
    28,
    36
   ],
   "distance": 72641.22127246068,
   "num_satellites": 16,
   "true_distance": 3358.412858269221,
   "number_of_congested_satellites": {
    "low": 30,
    "medium": 0,
    "high": 0
   },
   "number_of_delayed_satellites": {
    "low": 0,
    "medium": 14,
    "high": 16
   }
  },
  "flood": {
   "path": [
    [
     7,
     0
    ],
    [
     7,
     1
    ],
    [
     7,
     6
    ],
    [
     7,
     8
    ],
    [
     7,
     10
    ],
    [
     7,
     13
    ],
    [
     7,
     17
    ],
    [
     7,
     22
    ],
    [
     7,
     24
    ],
    [
     7,
     28
    ],
    [
     7,
     32
    ],
    [
     7,
     34
    ],
    [
     7,
     35
    ],
    [
     7,
     36
    ]
   ],
   "distance": 65070.27124182395,
   "num_satellites": 14,
   "true_distance": 3358.412858269221,
   "number_of_congested_satellites": {
    "low": 28,
    "medium": 0,
    "high": 0
   },
   "number_of_delayed_satellites": {
    "low": 0,
    "medium": 16,
    "high": 12
   }
  },
  "dqn": {
   "path": [
    7,
    36
   ],
   "distance": 3358.412858269221,
   "num_satellites": 2,
   "true_distance": 3358.412858269221,
   "number_of_congested_satellites": {
    "low": 2,
    "medium": 0,
    "high": 0
   },
   "number_of_delayed_satellites": {
    "low": 0,
    "medium": 2,
    "high": 0
   }
  }
 }
]